Metadata-Version: 1.0
Name: distfunc
Version: 0.1
Summary: Gaussian & Binomial distributions
Home-page: UNKNOWN
Author: fgrassi
Author-email: UNKNOWN
License: UNKNOWN
Platform: UNKNOWN
